.DS_Store
.gitignore
README.md
setup.cfg
setup.py
opencache/__init__.py
opencache/controller/__init__.py
opencache/controller/opencachecontroller.py
opencache/controller/api/__init__.py
opencache/controller/api/opencachejsonrpc.py
opencache/controller/request/__init__.py
opencache/controller/request/opencachefloodlight.py
opencache/controller/state/__init__.py
opencache/controller/state/opencachemongodb.py
opencache/controller/state/opencacheredis.py
opencache_controller.egg-info/PKG-INFO
opencache_controller.egg-info/SOURCES.txt
opencache_controller.egg-info/dependency_links.txt
opencache_controller.egg-info/namespace_packages.txt
opencache_controller.egg-info/requires.txt
opencache_controller.egg-info/top_level.txt
scripts/opencache-controller